setup.py
setsrng/__init__.py
setsrng/setsrng.py
setsrng.egg-info/PKG-INFO
setsrng.egg-info/SOURCES.txt
setsrng.egg-info/dependency_links.txt
setsrng.egg-info/top_level.txt